[
  {
    "code": 0,
    "message": "0",
    "ttl": 1,
    "data": {
      "cursor": {
        "is_end": true,
        "id": 834160973668367,
        "time": 1750774129
      },
      "items": [
        {
          "id": 834160973668367,
          "user": {
            "mid": 3546388174473844,
            "fans": 0,
            "nickname": "消费师",
            "avatar": "https://i1.hdslb.com/bfs/face/8e1046a772d1b98203874145cfd6ac18c83c3fd1.jpg",
            "mid_link": "",
            "follow": false
          },
          "item": {
            "type": "reply",
            "business": "评论",
            "business_id": 1,
            "title": "【明日之后】抽奖！典藏狙+20次！不愁不够卖了！",
            "image": "http://i0.hdslb.com/bfs/archive/b9e0bb94a41a9c0df34aef7b571b072d436f7ab3.jpg",
            "uri": "https://www.bilibili.com/video/BV1QNNCziEAg",
            "subject_id": 114718576484307,
            "root_id": 0,
            "target_id": 0,
            "source_id": 266593650128,
            "source_content": "@Donntest 。",
            "native_uri": "bilibili://video/114718576484307?page=0&comment_root_id=266593650128",
            "at_details": [
              {
                "mid": 431807064,
                "fans": 0,
                "nickname": "Donntest",
                "avatar": "https://i0.hdslb.com/bfs/face/member/noface.jpg",
                "mid_link": "",
                "follow": false
              }
            ],
            "topic_details": [],
            "hide_reply_button": false
          },
          "at_time": 1750774129
        }
      ]
    }
  }
]